matrix_class/__init__.py
matrix_class/exceptions.py
matrix_class/matrix.py
matrix_class-0.2.0.dist-info/METADATA
matrix_class-0.2.0.dist-info/WHEEL
matrix_class-0.2.0.dist-info/RECORD
