Metadata-Version: 2.1
Name: matrix_class
Version: 0.2.0
Summary: Matrix on class
License: MIT
Author: Kacper Bukowski
Author-email: kacperbuko@wp.pl
Requires-Python: >=3.8,<4.0
Classifier: License :: OSI Approved :: MIT License
Classifier: Operating System :: OS Independent
Classifier: Programming Language :: Python :: 3
Classifier: Programming Language :: Python :: 3.8
Classifier: Programming Language :: Python :: 3.9
Classifier: Programming Language :: Python :: 3.10
Classifier: Programming Language :: Python :: 3.11
Classifier: Programming Language :: Python :: 3.12
